{
  "metadata": {
    "source_document": "MMA140.md",
    "course_code": "MMA140",
    "course_title": "Spectral Theory and Operator Algebras",
    "department": "Department of Mathematical Sciences",
    "credits": "7.5",
    "iteration": "Spring 2025",
    "study_pace": "50%",
    "time": "Day",
    "location": "Göteborg",
    "study_form": "Campus",
    "language_of_instruction": "English",
    "duration": "24 Mar 2025 - 8 Jun 2025",
    "application_period": "16 Sep 2024 - 15 Oct 2024",
    "application_code": "GU-17038",
    "content_type": "course"
  },
  "sections": {
    "About": "In this course you will see a comprehensive treatment of the theory of linear operators on infinite-dimensional spaces. Our fundamental problem is to calculate spectra of specific operators. The spectrum of bounded operators on Banach spaces is best studied within the context of Banach and in particular C^\\*-algebras, and a part of the course will be devoted to the theory of these algebras. You will also learn about the spectral theorem for normal operators and the Riesz theory of compact operators with applications.",
    "Entry requirements": "General entry requirements and the equivalent of the course MMA120 Functional Analysis.",
    "Selection": "All eligible applicants who have applied before the deadline will be granted a place.",
    "Tuition": "Full education cost: 15 998 SEK\n\nFirst payment: 15 998 SEK\n\n**No fees** are charged for EU and EEA citizens, Swedish residence permit holders and exchange students.\n\n[More information about tuition fees](https://www.gu.se/en/study-in-gothenburg/apply/tuition-fees)",
    "Additional information": "Last modified: 15 January 2025"
  }
}